<?xml version="1.0" encoding="ISO-8859-1"?>

<celestialobject>
    <general>
        <type>moon</type>
        <name>naiad</name>
        <parent>neptune</parent>
    </general>
    <parameter>
        <diameter>58</diameter>
        <!-- km -->
        <rotationperiod>0.294</rotationperiod>
        <!-- day -->
        <orbitperiod>0.294</orbitperiod>
        <!-- day -->
        <orbiteccentricity>0.0003</orbiteccentricity>
        <orbitinclinationtoecliptic>4.738</orbitinclinationtoecliptic>
        <!-- ° -->
        <distance>48227</distance>
        <!-- km -->
    </parameter>
</celestialobject>
