{
  "metadata": {
    "source": "World Bank API v2",
    "version": "1.0",
    "lastUpdated": "2026-01-01",
    "description": "Fallback country data when World Bank API is unavailable"
  },
  "countries": [
    {
      "code": "FRA",
      "name": "France",
      "region": "Europe & Central Asia",
      "incomeLevel": "High income",
      "capital": "Paris",
      "longitude": "2.3522",
      "latitude": "48.8566",
      "population": 67000000,
      "areaSqKm": 643801.0,
      "gdpUsd": 2800000000000.0,
      "gdpPerCapitaUsd": 41760.0,
      "currency": "EUR"
    },
    {
      "code": "USA",
      "name": "United States",
      "region": "North America",
      "incomeLevel": "High income",
      "capital": "Washington, D.C.",
      "longitude": "-77.0369",
      "latitude": "38.9072",
      "population": 331000000,
      "areaSqKm": 9833517.0,
      "gdpUsd": 25000000000000.0,
      "gdpPerCapitaUsd": 75500.0,
      "currency": "USD"
    },
    {
      "code": "CHN",
      "name": "China",
      "region": "East Asia & Pacific",
      "incomeLevel": "Upper middle income",
      "capital": "Beijing",
      "longitude": "116.4074",
      "latitude": "39.9042",
      "population": 1412000000,
      "areaSqKm": 9596961.0,
      "gdpUsd": 18000000000000.0,
      "gdpPerCapitaUsd": 12750.0,
      "currency": "CNY"
    },
    {
      "code": "DEU",
      "name": "Germany",
      "region": "Europe & Central Asia",
      "incomeLevel": "High income",
      "capital": "Berlin",
      "longitude": "13.4050",
      "latitude": "52.5200",
      "population": 83000000,
      "areaSqKm": 357114.0,
      "gdpUsd": 4200000000000.0,
      "gdpPerCapitaUsd": 50600.0,
      "currency": "EUR"
    },
    {
      "code": "JPN",
      "name": "Japan",
      "region": "East Asia & Pacific",
      "incomeLevel": "High income",
      "capital": "Tokyo",
      "longitude": "139.6917",
      "latitude": "35.6895",
      "population": 125000000,
      "areaSqKm": 377975.0,
      "gdpUsd": 5000000000000.0,
      "gdpPerCapitaUsd": 40000.0,
      "currency": "JPY"
    },
    {
      "code": "GBR",
      "name": "United Kingdom",
      "region": "Europe & Central Asia",
      "incomeLevel": "High income",
      "capital": "London",
      "longitude": "-0.1278",
      "latitude": "51.5074",
      "population": 67000000,
      "areaSqKm": 242495.0,
      "gdpUsd": 3100000000000.0,
      "gdpPerCapitaUsd": 46250.0,
      "currency": "GBP"
    },
    {
      "code": "IND",
      "name": "India",
      "region": "South Asia",
      "incomeLevel": "Lower middle income",
      "capital": "New Delhi",
      "longitude": "77.2090",
      "latitude": "28.6139",
      "population": 1380000000,
      "areaSqKm": 3287263.0,
      "gdpUsd": 3400000000000.0,
      "gdpPerCapitaUsd": 2450.0,
      "currency": "INR"
    },
    {
      "code": "BRA",
      "name": "Brazil",
      "region": "Latin America & Caribbean",
      "incomeLevel": "Upper middle income",
      "capital": "Brasília",
      "longitude": "-47.8825",
      "latitude": "-15.7939",
      "population": 213000000,
      "areaSqKm": 8515767.0,
      "gdpUsd": 1900000000000.0,
      "gdpPerCapitaUsd": 8920.0,
      "currency": "BRL"
    },
    {
      "code": "CAN",
      "name": "Canada",
      "region": "North America",
      "incomeLevel": "High income",
      "capital": "Ottawa",
      "longitude": "-75.6972",
      "latitude": "45.4215",
      "population": 38000000,
      "areaSqKm": 9984670.0,
      "gdpUsd": 2000000000000.0,
      "gdpPerCapitaUsd": 52600.0,
      "currency": "CAD"
    },
    {
      "code": "AUS",
      "name": "Australia",
      "region": "East Asia & Pacific",
      "incomeLevel": "High income",
      "capital": "Canberra",
      "longitude": "149.1300",
      "latitude": "-35.2809",
      "population": 26000000,
      "areaSqKm": 7692024.0,
      "gdpUsd": 1700000000000.0,
      "gdpPerCapitaUsd": 65380.0,
      "currency": "AUD"
    }
  ]
}
